{"type": "Feature", "id": 12510545, "geometry": {"type": "Point", "coordinates": [-69.746696, -51.621399]}, "properties": {"woe:id": 12510545, "woe:parent_id": 468756, "woe:name": "Rio Gallegos Highway Strip Airport", "woe:placetype": 14, "woe:placetype_name": "Airport", "woe:lang": "ENG", "iso:country": "AR", "meta:provider": ["geoplanet:7.3.1", "geoplanet:7.3.2", "geoplanet:7.4.0", "geoplanet:7.4.1", "geoplanet:7.5.1", "geoplanet:7.5.2", "geoplanet:7.6.0", "geoplanet:7.8.1", "geoplanet:7.9.0", "geoplanet:7.10.0", "geoplanet:8.0.0", "woeplanet:8.0.0"], "meta:indexed": "2020-08-20T21:02:08.233644", "meta:updated": "2020-10-14T11:52:12.560354", "woe:hierarchy": {"continent": 24865673, "country": 23424747, "town": 0, "planet": 1, "county": 20071073, "suburb": 0, "state": 2344694, "region": 0, "localadmin": 0}, "woe:timezone_id": 56043545, "woe:hash": "4qy6kfs581y0", "woe:centroid": [-69.746696, -51.621399], "geom:latitude": -51.621399, "geom:longitude": -69.746696, "geom:hash": "4qy6kfs581y0", "woe:latitude": -51.621399, "geom:centroid": [-69.746696, -51.621399], "woe:longitude": -69.746696, "woe:repo": "woeplanet-airport-ar", "geom:area": 0.0, "woe:scale": 19}}