{"type": "Feature", "id": 12523703, "geometry": {"type": "Point", "coordinates": [-58.533298, -34.616699]}, "properties": {"woe:id": 12523703, "woe:parent_id": 465704, "woe:name": "Saenz Pena Airport", "woe:placetype": 14, "woe:placetype_name": "Airport", "woe:lang": "ENG", "iso:country": "AR", "meta:provider": ["geoplanet:7.3.1", "geoplanet:7.3.2", "geoplanet:7.4.0", "geoplanet:7.4.1", "geoplanet:7.5.1", "geoplanet:7.5.2", "geoplanet:7.6.0", "geoplanet:7.8.1", "geoplanet:7.9.0", "geoplanet:7.10.0", "geoplanet:8.0.0", "woeplanet:8.0.0"], "meta:indexed": "2020-08-20T21:02:08.284467", "woe:alias_ENG_V": ["SZQ Airport", "SZQ"], "meta:updated": "2020-10-14T11:52:12.602704", "woe:hierarchy": {"continent": 24865673, "country": 23424747, "town": 0, "planet": 1, "county": 20070758, "suburb": 0, "state": 2344675, "region": 0, "localadmin": 0}, "woe:timezone_id": 56043551, "woe:hash": "69y7h41r579e", "woe:centroid": [-58.533298, -34.616699], "geom:latitude": -34.616699, "geom:longitude": -58.533298, "geom:hash": "69y7h41r579e", "woe:latitude": -34.616699, "geom:centroid": [-58.533298, -34.616699], "woe:longitude": -58.533298, "woe:repo": "woeplanet-airport-ar", "geom:area": 0.0, "woe:scale": 19}}