{"type": "Feature", "id": 12510475, "geometry": {"type": "Point", "coordinates": [-58.049999, -35.541698]}, "properties": {"woe:id": 12510475, "woe:parent_id": 466927, "woe:name": "Chascomus Airport", "woe:placetype": 14, "woe:placetype_name": "Airport", "woe:lang": "ENG", "iso:country": "AR", "meta:provider": ["geoplanet:7.3.1", "geoplanet:7.3.2", "geoplanet:7.4.0", "geoplanet:7.4.1", "geoplanet:7.5.1", "geoplanet:7.5.2", "geoplanet:7.6.0", "geoplanet:7.8.1", "geoplanet:7.9.0", "geoplanet:7.10.0", "geoplanet:8.0.0", "woeplanet:8.0.0"], "meta:indexed": "2020-08-20T21:02:08.179725", "meta:updated": "2020-10-14T11:52:12.541398", "woe:hierarchy": {"continent": 24865673, "country": 23424747, "town": 0, "planet": 1, "county": 20070958, "suburb": 0, "state": 2344675, "region": 0, "localadmin": 0}, "woe:timezone_id": 56043551, "woe:hash": "69wtz1c68gr3", "woe:centroid": [-58.049999, -35.541698], "geom:latitude": -35.541698, "geom:longitude": -58.049999, "geom:hash": "69wtz1c68gr3", "woe:latitude": -35.541698, "geom:centroid": [-58.049999, -35.541698], "woe:longitude": -58.049999, "woe:repo": "woeplanet-airport-ar", "geom:area": 0.0, "woe:scale": 19}}