{"type": "Feature", "id": 12523565, "geometry": {"type": "Point", "coordinates": [-71.155602, -42.0681]}, "properties": {"woe:id": 12523565, "woe:parent_id": 332544, "woe:name": "El Maiten Airport", "woe:placetype": 14, "woe:placetype_name": "Airport", "woe:lang": "ENG", "iso:country": "AR", "meta:provider": ["geoplanet:7.3.1", "geoplanet:7.3.2", "geoplanet:7.4.0", "geoplanet:7.4.1", "geoplanet:7.5.1", "geoplanet:7.5.2", "geoplanet:7.6.0", "geoplanet:7.8.1", "geoplanet:7.9.0", "geoplanet:7.10.0", "geoplanet:8.0.0", "woeplanet:8.0.0"], "meta:indexed": "2020-08-20T21:02:08.271929", "woe:alias_ENG_V": ["EMX Airport", "EMX"], "meta:updated": "2020-10-14T11:52:12.607268", "woe:hierarchy": {"continent": 24865673, "country": 23424747, "town": 0, "planet": 1, "county": 20071050, "suburb": 0, "state": 2344678, "region": 0, "localadmin": 0}, "woe:timezone_id": 56043540, "woe:hash": "62t2svdpd3c8", "woe:centroid": [-71.155602, -42.0681], "geom:latitude": -42.0681, "geom:longitude": -71.155602, "geom:hash": "62t2svdpd3c8", "woe:latitude": -42.0681, "geom:centroid": [-71.155602, -42.0681], "woe:longitude": -71.155602, "woe:repo": "woeplanet-airport-ar", "geom:area": 0.0, "woe:scale": 19}}