{"type": "Feature", "id": 12523535, "properties": {"woe:id": 12523535, "woe:parent_id": 467172, "woe:name": "Charata Airport", "woe:placetype": 14, "woe:placetype_name": "Airport", "woe:lang": "ENG", "iso:country": "AR", "meta:provider": ["geoplanet:7.3.1", "geoplanet:7.3.2", "geoplanet:7.4.0", "geoplanet:7.4.1", "geoplanet:7.5.1", "geoplanet:7.5.2", "geoplanet:7.6.0", "geoplanet:7.8.1", "geoplanet:7.9.0", "geoplanet:7.10.0", "geoplanet:8.0.0", "woeplanet:8.0.0"], "meta:indexed": "2020-08-20T21:02:08.269025", "woe:alias_ENG_V": ["CNT Airport", "CNT"], "meta:updated": "2020-08-22T01:55:55.751630", "woe:hierarchy": {"continent": 24865673, "country": 23424747, "town": 0, "planet": 1, "county": 20070649, "suburb": 0, "state": 2344677, "region": 0, "localadmin": 0}, "woe:timezone_id": 56043541, "woe:hash": "6ehmnvr75rqs", "woe:centroid": [-61.216702, -27.2167], "geom:latitude": -27.2167, "geom:longitude": -61.216702, "geom:hash": "6ehmnvr75rqs", "woe:latitude": -27.2167, "geom:centroid": [-61.216702, -27.2167], "woe:longitude": -61.216702, "woe:repo": "woeplanet-airport-ar"}, "geometry": {"coordinates": [-61.216702, -27.2167], "type": "Point"}}