{"type": "Feature", "id": 12510501, "properties": {"woe:id": 12510501, "woe:parent_id": 466974, "woe:name": "General Roca Airport", "woe:placetype": 14, "woe:placetype_name": "Airport", "woe:lang": "ENG", "iso:country": "AR", "meta:provider": ["geoplanet:7.3.1", "geoplanet:7.3.2", "geoplanet:7.4.0", "geoplanet:7.4.1", "geoplanet:7.5.1", "geoplanet:7.5.2", "geoplanet:7.6.0", "geoplanet:7.8.1", "geoplanet:7.9.0", "geoplanet:7.10.0", "geoplanet:8.0.0", "woeplanet:8.0.0"], "meta:indexed": "2020-08-20T21:02:08.199132", "woe:alias_ENG_V": ["GNR Airport", "GNR"], "meta:updated": "2020-08-22T01:55:55.715214", "woe:hierarchy": {"continent": 24865673, "country": 23424747, "town": 0, "planet": 1, "county": 20071007, "suburb": 0, "state": 2344690, "region": 0, "localadmin": 0}, "woe:timezone_id": 56043546, "woe:hash": "63pfjkzbug12", "woe:centroid": [-67.610001, -38.9972], "geom:latitude": -38.9972, "geom:longitude": -67.610001, "geom:hash": "63pfjkzbug12", "woe:latitude": -38.9972, "geom:centroid": [-67.610001, -38.9972], "woe:longitude": -67.610001, "woe:repo": "woeplanet-airport-ar"}, "geometry": {"coordinates": [-67.610001, -38.9972], "type": "Point"}}