{"type": "Feature", "id": 12510504, "properties": {"woe:id": 12510504, "woe:parent_id": 466926, "woe:name": "Gobernador Gordillo Airport", "woe:placetype": 14, "woe:placetype_name": "Airport", "woe:lang": "ENG", "iso:country": "AR", "meta:provider": ["geoplanet:7.3.1", "geoplanet:7.3.2", "geoplanet:7.4.0", "geoplanet:7.4.1", "geoplanet:7.5.1", "geoplanet:7.5.2", "geoplanet:7.6.0", "geoplanet:7.8.1", "geoplanet:7.9.0", "geoplanet:7.10.0", "geoplanet:8.0.0", "woeplanet:8.0.0"], "meta:indexed": "2020-08-20T21:02:08.201635", "meta:updated": "2020-08-22T01:55:55.716526", "woe:hierarchy": {"continent": 24865673, "country": 23424747, "town": 0, "planet": 1, "county": 20070700, "suburb": 0, "state": 2344686, "region": 0, "localadmin": 0}, "woe:timezone_id": 56043543, "woe:hash": "6d8g798yhpg5", "woe:centroid": [-66.290298, -30.356899], "geom:latitude": -30.356899, "geom:longitude": -66.290298, "geom:hash": "6d8g798yhpg5", "woe:latitude": -30.356899, "geom:centroid": [-66.290298, -30.356899], "woe:longitude": -66.290298, "woe:repo": "woeplanet-airport-ar"}, "geometry": {"coordinates": [-66.290298, -30.356899], "type": "Point"}}