{"type": "Feature", "id": 12510541, "geometry": {"type": "Point", "coordinates": [-68.909698, -37.3806]}, "properties": {"woe:id": 12510541, "woe:parent_id": 22529482, "woe:name": "Rincon de Los Sauces Airport", "woe:placetype": 14, "woe:placetype_name": "Airport", "woe:lang": "ENG", "iso:country": "AR", "meta:provider": ["geoplanet:7.3.1", "geoplanet:7.3.2", "geoplanet:7.4.0", "geoplanet:7.4.1", "geoplanet:7.5.1", "geoplanet:7.5.2", "geoplanet:7.6.0", "geoplanet:7.8.1", "geoplanet:7.9.0", "geoplanet:7.10.0", "geoplanet:8.0.0", "woeplanet:8.0.0"], "meta:indexed": "2020-08-20T21:02:08.230471", "woe:alias_ENG_V": ["Rincon Los Sauces Airport", "RDS", "RDS Airport", "Rincon Los Sauces"], "meta:updated": "2020-10-14T11:52:12.563525", "woe:hierarchy": {"continent": 24865673, "country": 23424747, "town": 0, "planet": 1, "county": 20071035, "suburb": 0, "state": 2344689, "region": 0, "localadmin": 0}, "woe:timezone_id": 56043546, "woe:hash": "63qgrgj6pxhg", "woe:centroid": [-68.909698, -37.3806], "geom:latitude": -37.3806, "geom:longitude": -68.909698, "geom:hash": "63qgrgj6pxhg", "woe:latitude": -37.3806, "geom:centroid": [-68.909698, -37.3806], "woe:longitude": -68.909698, "woe:repo": "woeplanet-airport-ar", "geom:area": 0.0, "woe:scale": 19}}