{"type": "Feature", "id": 12510499, "properties": {"woe:id": 12510499, "woe:parent_id": 26795739, "woe:name": "General Enrique Mosconi Airport", "woe:placetype": 14, "woe:placetype_name": "Airport", "woe:lang": "ENG", "iso:country": "AR", "meta:provider": ["geoplanet:7.3.1", "geoplanet:7.3.2", "geoplanet:7.4.0", "geoplanet:7.4.1", "geoplanet:7.5.1", "geoplanet:7.5.2", "geoplanet:7.6.0", "geoplanet:7.8.1", "geoplanet:7.9.0", "geoplanet:7.10.0", "geoplanet:8.0.0", "woeplanet:8.0.0"], "meta:indexed": "2020-08-20T21:02:08.197394", "woe:alias_ENG_V": ["CRD Airport", "CRD"], "meta:updated": "2020-08-22T01:55:55.714358", "woe:hierarchy": {"continent": 24865673, "country": 23424747, "town": 0, "planet": 1, "county": 20071061, "suburb": 0, "state": 2344678, "region": 0, "localadmin": 0}, "woe:timezone_id": 56043540, "woe:hash": "4xb58ben4z55", "woe:centroid": [-67.462799, -45.787201], "geom:latitude": -45.787201, "geom:longitude": -67.462799, "geom:hash": "4xb58ben4z55", "woe:latitude": -45.787201, "geom:centroid": [-67.462799, -45.787201], "woe:longitude": -67.462799, "woe:repo": "woeplanet-airport-ar"}, "geometry": {"coordinates": [-67.462799, -45.787201], "type": "Point"}}