{"type": "Feature", "id": 12510525, "properties": {"woe:id": 12510525, "woe:parent_id": 466878, "woe:name": "Necochea Airport", "woe:placetype": 14, "woe:placetype_name": "Airport", "woe:lang": "ENG", "iso:country": "AR", "meta:provider": ["geoplanet:7.3.1", "geoplanet:7.3.2", "geoplanet:7.4.0", "geoplanet:7.4.1", "geoplanet:7.5.1", "geoplanet:7.5.2", "geoplanet:7.6.0", "geoplanet:7.8.1", "geoplanet:7.9.0", "geoplanet:7.10.0", "geoplanet:8.0.0", "woeplanet:8.0.0"], "meta:indexed": "2020-08-20T21:02:08.218164", "woe:alias_ENG_V": ["NEC Airport", "NEC"], "meta:updated": "2020-08-22T01:55:55.725486", "woe:hierarchy": {"continent": 24865673, "country": 23424747, "town": 0, "planet": 1, "county": 20070983, "suburb": 0, "state": 2344675, "region": 0, "localadmin": 0}, "woe:timezone_id": 56043551, "woe:hash": "69njj95g3pt4", "woe:centroid": [-58.815601, -38.490002], "geom:latitude": -38.490002, "geom:longitude": -58.815601, "geom:hash": "69njj95g3pt4", "woe:latitude": -38.490002, "geom:centroid": [-58.815601, -38.490002], "woe:longitude": -58.815601, "woe:repo": "woeplanet-airport-ar"}, "geometry": {"coordinates": [-58.815601, -38.490002], "type": "Point"}}